[
  {
    "user_agent": "Mozilla/5.0 (Windows NT 10.0; Win64; x64) AppleWebKit/537.36 (KHTML, like Gecko) Chrome/144.0.0.0 Safari/537.36",
    "accept": "text/html,application/xhtml+xml,application/xml;q=0.9,image/avif,image/webp,image/apng,*/*;q=0.8,application/signed-exchange;v=b3;q=0.7",
    "accept_language": "en-US,en;q=0.9",
    "accept_encoding": "gzip, deflate, br, zstd",
    "sec_ch_ua": "\"Google Chrome\";v=\"144\", \"Chromium\";v=\"144\", \"Not=A?Brand\";v=\"24\"",
    "sec_ch_ua_mobile": "?0",
    "sec_ch_ua_platform": "\"Windows\"",
    "sec_fetch_dest": "document",
    "sec_fetch_mode": "navigate",
    "sec_fetch_site": "none",
    "sec_fetch_user": "?1",
    "upgrade_insecure_requests": "1",
    "cache_control": "max-age=0",
    "pragma": "no-cache",
    "browser": "chrome",
    "os": "windows",
    "timestamp": "2026-02-05T10:09:21.025462+00:00"
  },
  {
    "user_agent": "Mozilla/5.0 (Macintosh; Intel Mac OS X 10_15_7) AppleWebKit/537.36 (KHTML, like Gecko) Chrome/144.0.0.0 Safari/537.36",
    "accept": "text/html,application/xhtml+xml,application/xml;q=0.9,image/avif,image/webp,image/apng,*/*;q=0.8,application/signed-exchange;v=b3;q=0.7",
    "accept_language": "en-US,en;q=0.9",
    "accept_encoding": "gzip, deflate, br, zstd",
    "sec_ch_ua": "\"Google Chrome\";v=\"144\", \"Chromium\";v=\"144\", \"Not=A?Brand\";v=\"24\"",
    "sec_ch_ua_mobile": "?0",
    "sec_ch_ua_platform": "\"macOS\"",
    "sec_fetch_dest": "document",
    "sec_fetch_mode": "navigate",
    "sec_fetch_site": "none",
    "sec_fetch_user": "?1",
    "upgrade_insecure_requests": "1",
    "cache_control": "max-age=0",
    "pragma": "no-cache",
    "browser": "chrome",
    "os": "macos",
    "timestamp": "2026-02-05T10:09:21.025498+00:00"
  },
  {
    "user_agent": "Mozilla/5.0 (X11; Linux x86_64) AppleWebKit/537.36 (KHTML, like Gecko) Chrome/144.0.0.0 Safari/537.36",
    "accept": "text/html,application/xhtml+xml,application/xml;q=0.9,image/avif,image/webp,image/apng,*/*;q=0.8,application/signed-exchange;v=b3;q=0.7",
    "accept_language": "en-US,en;q=0.9",
    "accept_encoding": "gzip, deflate, br, zstd",
    "sec_ch_ua": "\"Google Chrome\";v=\"144\", \"Chromium\";v=\"144\", \"Not=A?Brand\";v=\"24\"",
    "sec_ch_ua_mobile": "?0",
    "sec_ch_ua_platform": "",
    "sec_fetch_dest": "document",
    "sec_fetch_mode": "navigate",
    "sec_fetch_site": "none",
    "sec_fetch_user": "?1",
    "upgrade_insecure_requests": "1",
    "cache_control": "max-age=0",
    "pragma": "no-cache",
    "browser": "chrome",
    "os": "linux",
    "timestamp": "2026-02-05T10:09:21.025505+00:00"
  },
  {
    "user_agent": "Mozilla/5.0 (Windows NT 10.0; Win64; x64; rv:147.0) Gecko/20100101 Firefox/147.0",
    "accept": "text/html,application/xhtml+xml,application/xml;q=0.9,image/avif,image/webp,*/*;q=0.8",
    "accept_language": "en-US,en;q=0.5",
    "accept_encoding": "gzip, deflate, br",
    "sec_ch_ua": "",
    "sec_ch_ua_mobile": "?0",
    "sec_ch_ua_platform": "",
    "sec_fetch_dest": "document",
    "sec_fetch_mode": "navigate",
    "sec_fetch_site": "none",
    "sec_fetch_user": "?1",
    "upgrade_insecure_requests": "1",
    "cache_control": "max-age=0",
    "pragma": "no-cache",
    "browser": "firefox",
    "os": "windows",
    "timestamp": "2026-02-05T10:09:21.025511+00:00"
  },
  {
    "user_agent": "Mozilla/5.0 (Macintosh; Intel Mac OS X 15.7; rv:147.0) Gecko/20100101 Firefox/147.0",
    "accept": "text/html,application/xhtml+xml,application/xml;q=0.9,image/avif,image/webp,*/*;q=0.8",
    "accept_language": "en-US,en;q=0.5",
    "accept_encoding": "gzip, deflate, br",
    "sec_ch_ua": "",
    "sec_ch_ua_mobile": "?0",
    "sec_ch_ua_platform": "",
    "sec_fetch_dest": "document",
    "sec_fetch_mode": "navigate",
    "sec_fetch_site": "none",
    "sec_fetch_user": "?1",
    "upgrade_insecure_requests": "1",
    "cache_control": "max-age=0",
    "pragma": "no-cache",
    "browser": "firefox",
    "os": "macos",
    "timestamp": "2026-02-05T10:09:21.025515+00:00"
  },
  {
    "user_agent": "Mozilla/5.0 (X11; Linux i686; rv:147.0) Gecko/20100101 Firefox/147.0",
    "accept": "text/html,application/xhtml+xml,application/xml;q=0.9,image/avif,image/webp,*/*;q=0.8",
    "accept_language": "en-US,en;q=0.5",
    "accept_encoding": "gzip, deflate, br",
    "sec_ch_ua": "",
    "sec_ch_ua_mobile": "?0",
    "sec_ch_ua_platform": "",
    "sec_fetch_dest": "document",
    "sec_fetch_mode": "navigate",
    "sec_fetch_site": "none",
    "sec_fetch_user": "?1",
    "upgrade_insecure_requests": "1",
    "cache_control": "max-age=0",
    "pragma": "no-cache",
    "browser": "firefox",
    "os": "linux",
    "timestamp": "2026-02-05T10:09:21.025518+00:00"
  },
  {
    "user_agent": "Mozilla/5.0 (Macintosh; Intel Mac OS X 15_7_3) AppleWebKit/605.1.15 (KHTML, like Gecko) Version/26.0 Safari/605.1.15",
    "accept": "text/html,application/xhtml+xml,application/xml;q=0.9,*/*;q=0.8",
    "accept_language": "en-US,en;q=0.9",
    "accept_encoding": "gzip, deflate, br",
    "sec_ch_ua": "",
    "sec_ch_ua_mobile": "?0",
    "sec_ch_ua_platform": "",
    "sec_fetch_dest": "document",
    "sec_fetch_mode": "navigate",
    "sec_fetch_site": "none",
    "sec_fetch_user": "?1",
    "upgrade_insecure_requests": "1",
    "cache_control": "max-age=0",
    "pragma": "no-cache",
    "browser": "safari",
    "os": "macos",
    "timestamp": "2026-02-05T10:09:21.025522+00:00"
  }
]